speller3x/__init__.py
speller3x/checker.py
speller3x/english.txt
speller3x/francais.txt
speller3x/french.txt
speller3x/german.txt
speller3x/italian.txt
speller3x/spanish.txt
spell_checker-1.6.1.dist-info/LICENSE
spell_checker-1.6.1.dist-info/METADATA
spell_checker-1.6.1.dist-info/WHEEL
spell_checker-1.6.1.dist-info/top_level.txt
spell_checker-1.6.1.dist-info/RECORD
