Metadata-Version: 2.1
Name: spell-checker
Version: 1.6.1
Summary: Python 3+ spell checker, supports English, German, Italian, Spanish, and French!
Home-page: https://github.com/Harvard90873/data_structures
Author: Harvard90873
Author-email: harvard90873@gmail.com
License: MIT
Platform: UNKNOWN
Classifier: License :: OSI Approved :: MIT License
Classifier: Programming Language :: Python :: 3.9
Classifier: Programming Language :: Python :: 3
Requires-Dist: python-algorithms-3x
Requires-Dist: termcolor
Requires-Dist: data-structures3x
Requires-Dist: and-or-not
